advent/__init__.py
advent/__main__.py
advent/_config_reader.py
advent/_data_handle.py
advent/_downloader.py
advent/_pedantics.py
advent/_py_interface.py
advent/_typeshack.py
advent_tools-1.0.0a2.dist-info/METADATA
advent_tools-1.0.0a2.dist-info/WHEEL
advent_tools-1.0.0a2.dist-info/licenses/LICENSE
advent_tools-1.0.0a2.dist-info/RECORD
